LICENSE
CONTRIBUTORS
swmm_toolkit-0.16.2.dist-info/RECORD
swmm_toolkit-0.16.2.dist-info/WHEEL
swmm_toolkit-0.16.2.dist-info/METADATA
swmm_toolkit-0.16.2.dist-info/licenses/LICENSE.md
swmm_toolkit-0.16.2.dist-info/licenses/AUTHORS
swmm_toolkit-0.16.2.dist-info/licenses/extern/openmp.LICENSE
swmm/toolkit/shared_enum.py
swmm/toolkit/_solver.abi3.so
swmm/toolkit/solver.py
swmm/toolkit/_output.abi3.so
swmm/toolkit/libomp.dylib
swmm/toolkit/__init__.py
swmm/toolkit/libswmm5.dylib
swmm/toolkit/libswmm-output.dylib
swmm/toolkit/output.py
swmm/toolkit/output_metadata.py
