Metadata-Version: 2.4
Name: swmm-toolkit
Version: 0.16.2
Summary: PySWMM SWMM Python Toolkit
Keywords: swmm5,swmm,stormwater,hydraulics,hydrology
Author: See AUTHORS
Maintainer-Email: Unknown <bemcdonnell@gmail.com>
License-Expression: CC0-1.0 AND (MIT OR Apache-2.0)
License-File: AUTHORS
License-File: LICENSE.md
License-File: extern/openmp.LICENSE
Classifier: Topic :: Scientific/Engineering
Classifier: Operating System :: Microsoft :: Windows
Classifier: Operating System :: POSIX :: Linux
Classifier: Operating System :: MacOS
Classifier: Programming Language :: Python :: 3.9
Classifier: Programming Language :: Python :: 3.10
Classifier: Programming Language :: Python :: 3.11
Classifier: Programming Language :: Python :: 3.12
Classifier: Programming Language :: Python :: 3.13
Classifier: Programming Language :: C
Classifier: Development Status :: 5 - Production/Stable
Project-URL: Homepage, https://github.com/pyswmm/swmm-python
Requires-Python: >=3.9
Requires-Dist: aenum>=3.1.11
